setup.py
json2cpp/__init__.py
json2cpp/json2cpp.py
json2cpp.egg-info/PKG-INFO
json2cpp.egg-info/SOURCES.txt
json2cpp.egg-info/dependency_links.txt
json2cpp.egg-info/requires.txt
json2cpp.egg-info/top_level.txt