Metadata-Version: 1.0
Name: json2cpp
Version: 1.0.0
Summary: A tool for JSON & C++ Mapping
Home-page: UNKNOWN
Author: nasacj
Author-email: cj.nasa@gmail.com
License: BSD License
Keywords: JSON,C++
Platform: any
